tiny_solver-0.7.0.dist-info/METADATA
tiny_solver-0.7.0.dist-info/WHEEL
tiny_solver/loss_functions/__init__.pyi
tiny_solver/tiny_solver.pyi
tiny_solver/py.typed
tiny_solver/__init__.py
tiny_solver/factors/__init__.pyi
tiny_solver/tiny_solver.abi3.so
tiny_solver-0.7.0.dist-info/RECORD
