Metadata-Version: 2.3
Name: tiny_solver
Version: 0.7.0
Classifier: Programming Language :: Rust
Classifier: Programming Language :: Python :: Implementation :: CPython
Classifier: Programming Language :: Python :: Implementation :: PyPy
Classifier: Programming Language :: Python :: 3.8
Classifier: Programming Language :: Python :: 3.9
Classifier: Programming Language :: Python :: 3.10
Classifier: Programming Language :: Python :: 3.11
Classifier: Programming Language :: Python :: 3.12
Requires-Dist: numpy
Summary: Factor graph solver
Keywords: factor-graph,ceres-solver,minisam
Home-Page: https://github.com/powei-lin/tiny-solver-rs
Author: Powei Lin <poweilin1994@gmail.com>
Author-email: Powei Lin <poweilin1994@gmail.com>
License: MIT OR Apache-2.0
Requires-Python: >=3.8
Project-URL: Source Code, https://github.com/powei-lin/tiny-solver-rs
